brew_manager.py
main.py
pip_manager.py
pipbrew_clearner-0.1.0.dist-info/LICENCE.md
pipbrew_clearner-0.1.0.dist-info/METADATA
pipbrew_clearner-0.1.0.dist-info/WHEEL
pipbrew_clearner-0.1.0.dist-info/entry_points.txt
pipbrew_clearner-0.1.0.dist-info/top_level.txt
pipbrew_clearner-0.1.0.dist-info/RECORD
