Metadata-Version: 2.2
Name: pipbrew-clearner
Version: 0.1.0
Summary: Interactive CLI tool to list and uninstall pip and Homebrew packages
Home-page: https://github.com/yourusername/pipbrew-clearner
Author: Your Name
Author-email: your.email@example.com
Classifier: Programming Language :: Python :: 3
Classifier: Operating System :: MacOS :: MacOS X
Classifier: License :: OSI Approved :: MIT License
Requires-Python: >=3.6
License-File: LICENCE.md
Dynamic: author
Dynamic: author-email
Dynamic: classifier
Dynamic: description
Dynamic: description-content-type
Dynamic: home-page
Dynamic: requires-python
Dynamic: summary
